astrotree/__init__.py
astrotree/adstree.py
astrotree/config.py
astrotree/main.py
astrotree-1.1.5.dist-info/LICENSE.txt
astrotree-1.1.5.dist-info/METADATA
astrotree-1.1.5.dist-info/WHEEL
astrotree-1.1.5.dist-info/entry_points.txt
astrotree-1.1.5.dist-info/top_level.txt
astrotree-1.1.5.dist-info/RECORD
