Metadata-Version: 2.1
Name: astrotree
Version: 1.1.5
Summary: ADS-powered reference tree-builder for the Astro community!
Home-page: https://github.com/arka378/astrotree
Author: Arka Ghosh
Author-email: arka378@gmail.com
Keywords: academic,references,development
Classifier: Development Status :: 5 - Production/Stable
Classifier: Intended Audience :: Science/Research
Classifier: Topic :: Scientific/Engineering :: Astronomy
Classifier: License :: OSI Approved :: MIT License
Classifier: Programming Language :: Python :: 3
Classifier: Programming Language :: Python :: 3.7
Classifier: Programming Language :: Python :: 3.8
Classifier: Programming Language :: Python :: 3.9
Classifier: Programming Language :: Python :: 3.10
Classifier: Programming Language :: Python :: 3 :: Only
Requires-Python: >=3.7, <4
License-File: LICENSE.txt
Requires-Dist: requests
Requires-Dist: treelib
Requires-Dist: argparse
